sferriol/wamp/__init__.py
sferriol/wamp/__main__.py
sferriol/wamp/app.py
sferriol/wamp/broker.py
sferriol/wamp/component.py
sferriol/wamp/mon.py
sferriol/wamp/service/__init__.py
sferriol/wamp/service/main.py
sferriol/wamp/util/__init__.py
sferriol/wamp/util/crossbar.py
sferriol/wamp/util/test.py
sferriol_wamp-0.2.2.dist-info/LICENSE
sferriol_wamp-0.2.2.dist-info/METADATA
sferriol_wamp-0.2.2.dist-info/WHEEL
sferriol_wamp-0.2.2.dist-info/entry_points.txt
sferriol_wamp-0.2.2.dist-info/top_level.txt
sferriol_wamp-0.2.2.dist-info/RECORD
