Metadata-Version: 2.1
Name: sferriol-wamp
Version: 0.2.2
Summary: WAMP utilities
Requires-Python: <3.12,>=3.11.0
License-File: LICENSE
Requires-Dist: autobahn >=23.1.1
Requires-Dist: cbor2 >=5.4.6
Requires-Dist: click >=8.1.3
Requires-Dist: sferriol-python >=0.5.0
Requires-Dist: tomli-w >=1.0.0
